{
  "id": "ML-A020401",
  "level": 3,
  "level_name": {
    "local": "Arrondissement",
    "en": "Arrondissement"
  },
  "name": {
    "local": "Kati",
    "en": "Kati",
    "slug": "kati-020401"
  },
  "code": {
    "id": "ML-A020401",
    "iso": null
  },
  "parent": {
    "id": "ML0204",
    "level": 2,
    "name": {
      "local": "Kati",
      "en": "Kati",
      "slug": "kati-ml0204"
    }
  },
  "ancestors": [
    {
      "id": "ML02",
      "level": 1,
      "name": {
        "local": "Koulikoro",
        "en": "Koulikoro",
        "slug": "koulikoro-ml02"
      }
    },
    {
      "id": "ML0204",
      "level": 2,
      "name": {
        "local": "Kati",
        "en": "Kati",
        "slug": "kati-ml0204"
      }
    }
  ],
  "children_count": {
    "commune": 9
  },
  "zip_codes": [],
  "geo": {
    "lat": "16.113",
    "lon": "-3.733"
  },
  "metadata": {},
  "source": {}
}