{
  "id": "ML-A050701",
  "level": 3,
  "level_name": {
    "local": "Arrondissement",
    "en": "Arrondissement"
  },
  "name": {
    "local": "Sofara",
    "en": "Sofara",
    "slug": "sofara-050701"
  },
  "code": {
    "id": "ML-A050701",
    "iso": null
  },
  "parent": {
    "id": "ML0507",
    "level": 2,
    "name": {
      "local": "Sofara",
      "en": "Sofara",
      "slug": "sofara-ml0507"
    }
  },
  "ancestors": [
    {
      "id": "ML05",
      "level": 1,
      "name": {
        "local": "Mopti",
        "en": "Mopti",
        "slug": "mopti-ml05"
      }
    },
    {
      "id": "ML0507",
      "level": 2,
      "name": {
        "local": "Sofara",
        "en": "Sofara",
        "slug": "sofara-ml0507"
      }
    }
  ],
  "children_count": {
    "commune": 1
  },
  "zip_codes": [],
  "geo": {
    "lat": "14.017",
    "lon": "-4.233"
  },
  "metadata": {},
  "source": {}
}