[
  {
    "id": "ML-C01080301",
    "level": 4,
    "level_name": {
      "local": "Commune",
      "en": "Commune"
    },
    "name": {
      "local": "Diallan",
      "en": "Diallan",
      "slug": "diallan-01080301"
    },
    "code": {
      "id": "ML-C01080301",
      "iso": null
    },
    "parent": {
      "id": "ML-A010803",
      "level": 3,
      "name": {
        "local": "Diallan",
        "en": "Diallan",
        "slug": "diallan-010803"
      }
    },
    "ancestors": [
      {
        "id": "ML01",
        "level": 1,
        "name": {
          "local": "Kayes",
          "en": "Kayes",
          "slug": "kayes-ml01"
        }
      },
      {
        "id": "ML0108",
        "level": 2,
        "name": {
          "local": "Oussoubidiagna",
          "en": "Oussoubidiagna",
          "slug": "oussoubidiagna-ml0108"
        }
      },
      {
        "id": "ML-A010803",
        "level": 3,
        "name": {
          "local": "Diallan",
          "en": "Diallan",
          "slug": "diallan-010803"
        }
      }
    ],
    "children_count": {},
    "zip_codes": [],
    "geo": {
      "lat": "14.245",
      "lon": "-10.462"
    },
    "metadata": {},
    "source": {}
  }
]