{
  "id": "ML-A060803",
  "level": 3,
  "level_name": {
    "local": "Arrondissement",
    "en": "Arrondissement"
  },
  "name": {
    "local": "Haribomo",
    "en": "Haribomo",
    "slug": "haribomo-060803"
  },
  "code": {
    "id": "ML-A060803",
    "iso": null
  },
  "parent": {
    "id": "ML0608",
    "level": 2,
    "name": {
      "local": "Bambara-Maoudé",
      "en": "Bambara-Maoude",
      "slug": "bambara-maoude-ml0608"
    }
  },
  "ancestors": [
    {
      "id": "ML06",
      "level": 1,
      "name": {
        "local": "Tombouctou",
        "en": "Timbuktu",
        "slug": "timbuktu-ml06"
      }
    },
    {
      "id": "ML0608",
      "level": 2,
      "name": {
        "local": "Bambara-Maoudé",
        "en": "Bambara-Maoude",
        "slug": "bambara-maoude-ml0608"
      }
    }
  ],
  "children_count": {
    "commune": 1
  },
  "zip_codes": [],
  "geo": {
    "lat": "15.851",
    "lon": "-2.786"
  },
  "metadata": {},
  "source": {}
}