[
  {
    "id": "ML-C09040301",
    "level": 4,
    "level_name": {
      "local": "Commune",
      "en": "Commune"
    },
    "name": {
      "local": "Erg-Lakhal",
      "en": "Erg-Lakhal",
      "slug": "erg-lakhal-09040301"
    },
    "code": {
      "id": "ML-C09040301",
      "iso": null
    },
    "parent": {
      "id": "ML-A090403",
      "level": 3,
      "name": {
        "local": "Erg-Lakhal",
        "en": "Erg-Lakhal",
        "slug": "erg-lakhal-090403"
      }
    },
    "ancestors": [
      {
        "id": "ML09",
        "level": 1,
        "name": {
          "local": "Taoudenni",
          "en": "Taoudenni",
          "slug": "taoudenni-ml09"
        }
      },
      {
        "id": "ML0904",
        "level": 2,
        "name": {
          "local": "Boû-Djebeha",
          "en": "Bou-Djebeha",
          "slug": "bou-djebeha-ml0904"
        }
      },
      {
        "id": "ML-A090403",
        "level": 3,
        "name": {
          "local": "Erg-Lakhal",
          "en": "Erg-Lakhal",
          "slug": "erg-lakhal-090403"
        }
      }
    ],
    "children_count": {},
    "zip_codes": [],
    "geo": {
      "lat": "22.677",
      "lon": "-3.979"
    },
    "metadata": {},
    "source": {}
  }
]